Metadata-Version: 1.1
Name: django-registration2
Version: 0.9.4
Summary: Registration and moderation utilites
Home-page: https://github.com/bruth/django-registration2
Author: Byron Ruth
Author-email: b@devel.io
License: BSD
Keywords: registration moderation
Platform: UNKNOWN
Classifier: Development Status :: 4 - Beta
Classifier: Framework :: Django
Classifier: Intended Audience :: Developers
Classifier: License :: OSI Approved :: BSD License
Classifier: Operating System :: OS Independent
Classifier: Programming Language :: Python
Classifier: Topic :: Internet :: WWW/HTTP
